runner/__init__.py
runner/job.py
runner/runner.py
toil_runner-1.2.8.dist-info/DESCRIPTION.rst
toil_runner-1.2.8.dist-info/METADATA
toil_runner-1.2.8.dist-info/RECORD
toil_runner-1.2.8.dist-info/WHEEL
toil_runner-1.2.8.dist-info/metadata.json
toil_runner-1.2.8.dist-info/top_level.txt
